uart_rx.vhd
library ieee;
use ieee.std_logic_1164.all;
use ieee.numeric_std.all;

entity uart_rx is
  generic (
    g_CLKS_PER_BIT : integer := 870
  );
  port (
    i_clk       : in  std_logic;
    i_rx_serial : in  std_logic;
    o_rx_dv     : out std_logic;
    o_rx_byte   : out std_logic_vector(7 downto 0)
  );
end uart_rx;

architecture rtl of uart_rx is
  type t_SM_Main is (IDLE, RX_START_BIT, RX_DATA_BITS, RX_STOP_BIT, CLEANUP);
  signal r_SM_Main : t_SM_Main := IDLE;

  signal r_Rx_Data_R : std_logic := '0';
  signal r_Rx_Data   : std_logic := '0';

  signal r_Clk_Count : integer range 0 to g_CLKS_PER_BIT-1 := 0;
  signal r_Bit_Index : integer range 0 to 7 := 0;
  signal r_Rx_Byte   : std_logic_vector(7 downto 0) := (others => '0');
  signal r_Rx_DV     : std_logic := '0';

begin
  -- Purpose: Double-register the incoming data for metastability issues
  p_SAMPLE : process (i_clk)
  begin
    if rising_edge(i_clk) then
      r_Rx_Data_R <= i_rx_serial;
      r_Rx_Data   <= r_Rx_Data_R;
    end if;
  end process p_SAMPLE;

  p_UART_RX : process (i_clk)
  begin
    if rising_edge(i_clk) then
      case r_SM_Main is

        when IDLE =>
          r_Rx_DV     <= '0';
          r_Clk_Count <= 0;
          r_Bit_Index <= 0;

          if r_Rx_Data = '0' then -- Start bit detected
            r_SM_Main <= RX_START_BIT;
          else
            r_SM_Main <= IDLE;
          end if;

        -- Check middle of start bit to confirm it's still low
        when RX_START_BIT =>
          if r_Clk_Count = (g_CLKS_PER_BIT-1)/2 then
            if r_Rx_Data = '0' then
              r_Clk_Count <= 0;  -- reset counter, found the middle
              r_SM_Main   <= RX_DATA_BITS;
            else
              r_SM_Main <= IDLE;
            end if;
          else
            r_Clk_Count <= r_Clk_Count + 1;
            r_SM_Main   <= RX_START_BIT;
          end if;

        when RX_DATA_BITS =>
          if r_Clk_Count < g_CLKS_PER_BIT-1 then
            r_Clk_Count <= r_Clk_Count + 1;
            r_SM_Main   <= RX_DATA_BITS;
          else
            r_Clk_Count            <= 0;
            r_Rx_Byte(r_Bit_Index) <= r_Rx_Data;

            if r_Bit_Index < 7 then
              r_Bit_Index <= r_Bit_Index + 1;
              r_SM_Main   <= RX_DATA_BITS;
            else
              r_Bit_Index <= 0;
              r_SM_Main   <= RX_STOP_BIT;
            end if;
          end if;

        when RX_STOP_BIT =>
          -- Wait g_CLKS_PER_BIT-1 (Stop Bit Duration)
          if r_Clk_Count < g_CLKS_PER_BIT-1 then
            r_Clk_Count <= r_Clk_Count + 1;
            r_SM_Main   <= RX_STOP_BIT;
          else
            r_Rx_DV     <= '1';
            r_Clk_Count <= 0;
            r_SM_Main   <= CLEANUP;
          end if;

        when CLEANUP =>
          r_SM_Main <= IDLE;
          r_Rx_DV   <= '0';

        when others =>
          r_SM_Main <= IDLE;
      end case;
    end if;
  end process p_UART_RX;

  o_rx_dv   <= r_Rx_DV;
  o_rx_byte <= r_Rx_Byte;
end rtl;

uart_tx.vhd
library ieee;
use ieee.std_logic_1164.all;
use ieee.numeric_std.all;

entity uart_tx is
  generic (
    g_CLKS_PER_BIT : integer := 870  -- (Frequency / BaudRate) already calculated by the user
  );
  port (
    i_clk       : in  std_logic;
    i_tx_dv     : in  std_logic; -- Data Valid pulse
    i_tx_byte   : in  std_logic_vector(7 downto 0);
    o_tx_active : out std_logic;
    o_tx_serial : out std_logic;
    o_tx_done   : out std_logic
  );
end uart_tx;

architecture rtl of uart_tx is
  type t_SM_Main is (IDLE, TX_START_BIT, TX_DATA_BITS, TX_STOP_BIT, CLEANUP);
  signal r_SM_Main : t_SM_Main := IDLE;

  signal r_Clk_Count : integer range 0 to g_CLKS_PER_BIT-1 := 0;
  signal r_Bit_Index : integer range 0 to 7 := 0;
  signal r_Tx_Data   : std_logic_vector(7 downto 0) := (others => '0');
  signal r_Tx_Done   : std_logic := '0';

begin
  p_UART_TX : process (i_clk)
  begin
    if rising_edge(i_clk) then
      case r_SM_Main is

        when IDLE =>
          o_tx_active <= '0';
          o_tx_serial <= '1'; -- Idle high
          r_Tx_Done   <= '0';
          r_Clk_Count <= 0;
          r_Bit_Index <= 0;

          if i_tx_dv = '1' then
            r_Tx_Data <= i_tx_byte;
            r_SM_Main <= TX_START_BIT;
          else
            r_SM_Main <= IDLE;
          end if;

        -- Send Start Bit (Low)
        when TX_START_BIT =>
          o_tx_active <= '1';
          o_tx_serial <= '0';

          if r_Clk_Count < g_CLKS_PER_BIT-1 then
            r_Clk_Count <= r_Clk_Count + 1;
            r_SM_Main   <= TX_START_BIT;
          else
            r_Clk_Count <= 0;
            r_SM_Main   <= TX_DATA_BITS;
          end if;

        -- Send Data Bits
        when TX_DATA_BITS =>
          o_tx_serial <= r_Tx_Data(r_Bit_Index);

          if r_Clk_Count < g_CLKS_PER_BIT-1 then
            r_Clk_Count <= r_Clk_Count + 1;
            r_SM_Main   <= TX_DATA_BITS;
          else
            r_Clk_Count <= 0;
            if r_Bit_Index < 7 then
              r_Bit_Index <= r_Bit_Index + 1;
              r_SM_Main   <= TX_DATA_BITS;
            else
              r_Bit_Index <= 0;
              r_SM_Main   <= TX_STOP_BIT;
            end if;
          end if;

        -- Send Stop Bit (High)
        when TX_STOP_BIT =>
          o_tx_serial <= '1';

          if r_Clk_Count < g_CLKS_PER_BIT-1 then
            r_Clk_Count <= r_Clk_Count + 1;
            r_SM_Main   <= TX_STOP_BIT;
          else
            r_Tx_Done   <= '1';
            r_Clk_Count <= 0;
            r_SM_Main   <= CLEANUP;
          end if;

        when CLEANUP =>
          o_tx_active <= '0';
          r_Tx_Done   <= '1';
          r_SM_Main   <= IDLE;

        when others =>
          r_SM_Main <= IDLE;
      end case;
    end if;
  end process p_UART_TX;

  o_tx_done <= r_Tx_Done;
end rtl;

uart_tb.vhd
library ieee;
use ieee.std_logic_1164.all;
use ieee.numeric_std.all;

entity uart_tb is
end uart_tb;

architecture behave of uart_tb is
  constant c_CLK_PERIOD : time := 10 ns; -- 100 MHz
  constant c_CLKS_PER_BIT : integer := 87; -- Number of clock cycles per bit this is calculated as 10 ns / (1/115200) = 87

  signal r_Clk : std_logic := '0';
  signal w_Tx_Serial : std_logic;

  -- TX Signals
  signal r_Tx_Dv   : std_logic := '0';
  signal r_Tx_Byte : std_logic_vector(7 downto 0) := (others => '0');
  signal w_Tx_Active : std_logic;
  signal w_Tx_Done   : std_logic;

  -- RX Signals
  signal w_Rx_Dv   : std_logic;
  signal w_Rx_Byte : std_logic_vector(7 downto 0);

begin
  -- Clock Generator
  r_Clk <= not r_Clk after c_CLK_PERIOD/2;


  UART_TX_INST : entity work.uart_tx
    generic map (g_CLKS_PER_BIT => c_CLKS_PER_BIT)
    port map (
      i_clk       => r_Clk,
      i_tx_dv     => r_Tx_Dv,
      i_tx_byte   => r_Tx_Byte,
      o_tx_active => w_Tx_Active,
      o_tx_serial => w_Tx_Serial,
      o_tx_done   => w_Tx_Done
    );

  -- Instantiate UART Receiver
  UART_RX_INST : entity work.uart_rx
    generic map (g_CLKS_PER_BIT => c_CLKS_PER_BIT)
    port map (
      i_clk       => r_Clk,
      i_rx_serial => w_Tx_Serial,
      o_rx_dv     => w_Rx_Dv,
      o_rx_byte   => w_Rx_Byte
    );

    -- Main Stimulus Process
      p_TEST : process
      begin
        wait until rising_edge(r_Clk);
        wait until rising_edge(r_Clk);

        -- Send a byte: 0x37 (00110111)
        r_Tx_Dv   <= '1';
        r_Tx_Byte <= X"10";
        wait until rising_edge(r_Clk);
        r_Tx_Dv   <= '0';


        wait until w_Rx_Dv = '1';


        assert w_Rx_Byte = X"10"
          report "Test Failed: Received wrong byte" severity failure;

        report "Test Passed: Sent 0x10 and Received " & to_hstring(w_Rx_Byte);

        wait for 1 us;

        assert false report "Simulation Finished Successfully";
        wait;
      end process;

end behave;

wave.vcd
$date
  Thu Dec 04 13:09:32 2025
$end
$version
  GHDL v0
$end
$timescale
  1 fs
$end
$scope module standard $end
$upscope $end
$scope module textio $end
$upscope $end
$scope module std_logic_1164 $end
$upscope $end
$scope module numeric_std $end
$upscope $end
$scope module uart_tb $end
$var reg 1 ! r_clk $end
$var reg 1 " w_tx_serial $end
$var reg 1 # r_tx_dv $end
$var reg 8 $ r_tx_byte[7:0] $end
$var reg 1 % w_tx_active $end
$var reg 1 & w_tx_done $end
$var reg 1 ' w_rx_dv $end
$var reg 8 ( w_rx_byte[7:0] $end
$scope module uart_tx_inst $end
$var reg 1 ) i_clk $end
$var reg 1 * i_tx_dv $end
$var reg 8 + i_tx_byte[7:0] $end
$var reg 1 , o_tx_active $end
$var reg 1 - o_tx_serial $end
$var reg 1 . o_tx_done $end
$comment r_sm_main is not handled $end
$var integer 32 / r_clk_count $end
$var integer 32 0 r_bit_index $end
$var reg 8 1 r_tx_data[7:0] $end
$var reg 1 2 r_tx_done $end
$upscope $end
$scope module uart_rx_inst $end
$var reg 1 3 i_clk $end
$var reg 1 4 i_rx_serial $end
$var reg 1 5 o_rx_dv $end
$var reg 8 6 o_rx_byte[7:0] $end
$comment r_sm_main is not handled $end
$var reg 1 7 r_rx_data_r $end
$var reg 1 8 r_rx_data $end
$var integer 32 9 r_clk_count $end
$var integer 32 : r_bit_index $end
$var reg 8 ; r_rx_byte[7:0] $end
$var reg 1 < r_rx_dv $end
$upscope $end
$upscope $end
$enddefinitions $end
#0
0!
U"
0#
b00000000 $
U%
0&
0'
b00000000 (
0)
0*
b00000000 +
U,
U-
0.
b0 /
b0 0
b00000000 1
02
03
U4
05
b00000000 6
07
08
b0 9
b0 :
b00000000 ;
0<
#5000000
1!
1"
0%
1)
0,
1-
13
14
U7
#10000000
0!
0)
03
#15000000
1!
1#
b00010000 $
1)
1*
b00010000 +
13
17
U8
b1 9
#20000000
0!
0)
03
#25000000
1!
0#
1)
0*
b00010000 1
13
18
b10 9
#30000000
0!
0)
03
#35000000
1!
0"
1%
1)
1,
0-
b1 /
13
04
b11 9
#40000000
0!
0)
03
#45000000
1!
1)
b10 /
13
07
b100 9
#50000000
0!
0)
03
#55000000
1!
1)
b11 /
13
08
b101 9
#60000000
0!
0)
03
#65000000
1!
1)
b100 /
13
b110 9
#70000000
0!
0)
03
#75000000
1!
1)
b101 /
13
b111 9
#80000000
0!
0)
03
#85000000
1!
1)
b110 /
13
b1000 9
#90000000
0!
0)
03
#95000000
1!
1)
b111 /
13
b1001 9
#100000000
0!
0)
03
#105000000
1!
1)
b1000 /
13
b1010 9
#110000000
0!
0)
03
#115000000
1!
1)
b1001 /
13
b1011 9
#120000000
0!
0)
03
#125000000
1!
1)
b1010 /
13
b1100 9
#130000000
0!
0)
03
#135000000
1!
1)
b1011 /
13
b1101 9
#140000000
0!
0)
03
#145000000
1!
1)
b1100 /
13
b1110 9
#150000000
0!
0)
03
#155000000
1!
1)
b1101 /
13
b1111 9
#160000000
0!
0)
03
#165000000
1!
1)
b1110 /
13
b10000 9
#170000000
0!
0)
03
#175000000
1!
1)
b1111 /
13
b10001 9
#180000000
0!
0)
03
#185000000
1!
1)
b10000 /
13
b10010 9
#190000000
0!
0)
03
#195000000
1!
1)
b10001 /
13
b10011 9
#200000000
0!
0)
03
#205000000
1!
1)
b10010 /
13
b10100 9
#210000000
0!
0)
03
#215000000
1!
1)
b10011 /
13
b10101 9
#220000000
0!
0)
03
#225000000
1!
1)
b10100 /
13
b10110 9
#230000000
0!
0)
03
#235000000
1!
1)
b10101 /
13
b10111 9
#240000000
0!
0)
03
#245000000
1!
1)
b10110 /
13
b11000 9
#250000000
0!
0)
03
#255000000
1!
1)
b10111 /
13
b11001 9
#260000000
0!
0)
03
#265000000
1!
1)
b11000 /
13
b11010 9
#270000000
0!
0)
03
#275000000
1!
1)
b11001 /
13
b11011 9
#280000000
0!
0)
03
#285000000
1!
1)
b11010 /
13
b11100 9
#290000000
0!
0)
03
#295000000
1!
1)
b11011 /
13
b11101 9
#300000000
0!
0)
03
#305000000
1!
1)
b11100 /
13
b11110 9
#310000000
0!
0)
03
#315000000
1!
1)
b11101 /
13
b11111 9
#320000000
0!
0)
03
#325000000
1!
1)
b11110 /
13
b100000 9
#330000000
0!
0)
03
#335000000
1!
1)
b11111 /
13
b100001 9
#340000000
0!
0)
03
#345000000
1!
1)
b100000 /
13
b100010 9
#350000000
0!
0)
03
#355000000
1!
1)
b100001 /
13
b100011 9
#360000000
0!
0)
03
#365000000
1!
1)
b100010 /
13
b100100 9
#370000000
0!
0)
03
#375000000
1!
1)
b100011 /
13
b100101 9
#380000000
0!
0)
03
#385000000
1!
1)
b100100 /
13
b100110 9
#390000000
0!
0)
03
#395000000
1!
1)
b100101 /
13
b100111 9
#400000000
0!
0)
03
#405000000
1!
1)
b100110 /
13
b101000 9
#410000000
0!
0)
03
#415000000
1!
1)
b100111 /
13
b101001 9
#420000000
0!
0)
03
#425000000
1!
1)
b101000 /
13
b101010 9
#430000000
0!
0)
03
#435000000
1!
1)
b101001 /
13
b101011 9
#440000000
0!
0)
03
#445000000
1!
1)
b101010 /
13
b0 9
#450000000
0!
0)
03
#455000000
1!
1)
b101011 /
13
b1 9
#460000000
0!
0)
03
#465000000
1!
1)
b101100 /
13
b10 9
#470000000
0!
0)
03
#475000000
1!
1)
b101101 /
13
b11 9
#480000000
0!
0)
03
#485000000
1!
1)
b101110 /
13
b100 9
#490000000
0!
0)
03
#495000000
1!
1)
b101111 /
13
b101 9
#500000000
0!
0)
03
#505000000
1!
1)
b110000 /
13
b110 9
#510000000
0!
0)
03
#515000000
1!
1)
b110001 /
13
b111 9
#520000000
0!
0)
03
#525000000
1!
1)
b110010 /
13
b1000 9
#530000000
0!
0)
03
#535000000
1!
1)
b110011 /
13
b1001 9
#540000000
0!
0)
03
#545000000
1!
1)
b110100 /
13
b1010 9
#550000000
0!
0)
03
#555000000
1!
1)
b110101 /
13
b1011 9
#560000000
0!
0)
03
#565000000
1!
1)
b110110 /
13
b1100 9
#570000000
0!
0)
03
#575000000
1!
1)
b110111 /
13
b1101 9
#580000000
0!
0)
03
#585000000
1!
1)
b111000 /
13
b1110 9
#590000000
0!
0)
03
#595000000
1!
1)
b111001 /
13
b1111 9
#600000000
0!
0)
03
#605000000
1!
1)
b111010 /
13
b10000 9
#610000000
0!
0)
03
#615000000
1!
1)
b111011 /
13
b10001 9
#620000000
0!
0)
03
#625000000
1!
1)
b111100 /
13
b10010 9
#630000000
0!
0)
03
#635000000
1!
1)
b111101 /
13
b10011 9
#640000000
0!
0)
03
#645000000
1!
1)
b111110 /
13
b10100 9
#650000000
0!
0)
03
#655000000
1!
1)
b111111 /
13
b10101 9
#660000000
0!
0)
03
#665000000
1!
1)
b1000000 /
13
b10110 9
#670000000
0!
0)
03
#675000000
1!
1)
b1000001 /
13
b10111 9
#680000000
0!
0)
03
#685000000
1!
1)
b1000010 /
13
b11000 9
#690000000
0!
0)
03
#695000000
1!
1)
b1000011 /
13
b11001 9
#700000000
0!
0)
03
#705000000
1!
1)
b1000100 /
13
b11010 9
#710000000
0!
0)
03
#715000000
1!
1)
b1000101 /
13
b11011 9
#720000000
0!
0)
03
#725000000
1!
1)
b1000110 /
13
b11100 9
#730000000
0!
0)
03
#735000000
1!
1)
b1000111 /
13
b11101 9
#740000000
0!
0)
03
#745000000
1!
1)
b1001000 /
13
b11110 9
#750000000
0!
0)
03
#755000000
1!
1)
b1001001 /
13
b11111 9
#760000000
0!
0)
03
#765000000
1!
1)
b1001010 /
13
b100000 9
#770000000
0!
0)
03
#775000000
1!
1)
b1001011 /
13
b100001 9
#780000000
0!
0)
03
#785000000
1!
1)
b1001100 /
13
b100010 9
#790000000
0!
0)
03
#795000000
1!
1)
b1001101 /
13
b100011 9
#800000000
0!
0)
03
#805000000
1!
1)
b1001110 /
13
b100100 9
#810000000
0!
0)
03
#815000000
1!
1)
b1001111 /
13
b100101 9
#820000000
0!
0)
03
#825000000
1!
1)
b1010000 /
13
b100110 9
#830000000
0!
0)
03
#835000000
1!
1)
b1010001 /
13
b100111 9
#840000000
0!
0)
03
#845000000
1!
1)
b1010010 /
13
b101000 9
#850000000
0!
0)
03
#855000000
1!
1)
b1010011 /
13
b101001 9
#860000000
0!
0)
03
#865000000
1!
1)
b1010100 /
13
b101010 9
#870000000
0!
0)
03
#875000000
1!
1)
b1010101 /
13
b101011 9
#880000000
0!
0)
03
#885000000
1!
1)
b1010110 /
13
b101100 9
#890000000
0!
0)
03
#895000000
1!
1)
b0 /
13
b101101 9
#900000000
0!
0)
03
#905000000
1!
1)
b1 /
13
b101110 9
#910000000
0!
0)
03
#915000000
1!
1)
b10 /
13
b101111 9
#920000000
0!
0)
03
#925000000
1!
1)
b11 /
13
b110000 9
#930000000
0!
0)
03
#935000000
1!
1)
b100 /
13
b110001 9
#940000000
0!
0)
03
#945000000
1!
1)
b101 /
13
b110010 9
#950000000
0!
0)
03
#955000000
1!
1)
b110 /
13
b110011 9
#960000000
0!
0)
03
#965000000
1!
1)
b111 /
13
b110100 9
#970000000
0!
0)
03
#975000000
1!
1)
b1000 /
13
b110101 9
#980000000
0!
0)
03
#985000000
1!
1)
b1001 /
13
b110110 9
#990000000
0!
0)
03
#995000000
1!
1)
b1010 /
13
b110111 9
#1000000000
0!
0)
03
#1005000000
1!
1)
b1011 /
13
b111000 9
#1010000000
0!
0)
03
#1015000000
1!
1)
b1100 /
13
b111001 9
#1020000000
0!
0)
03
#1025000000
1!
1)
b1101 /
13
b111010 9
#1030000000
0!
0)
03
#1035000000
1!
1)
b1110 /
13
b111011 9
#1040000000
0!
0)
03
#1045000000
1!
1)
b1111 /
13
b111100 9
#1050000000
0!
0)
03
#1055000000
1!
1)
b10000 /
13
b111101 9
#1060000000
0!
0)
03
#1065000000
1!
1)
b10001 /
13
b111110 9
#1070000000
0!
0)
03
#1075000000
1!
1)
b10010 /
13
b111111 9
#1080000000
0!
0)
03
#1085000000
1!
1)
b10011 /
13
b1000000 9
#1090000000
0!
0)
03
#1095000000
1!
1)
b10100 /
13
b1000001 9
#1100000000
0!
0)
03
#1105000000
1!
1)
b10101 /
13
b1000010 9
#1110000000
0!
0)
03
#1115000000
1!
1)
b10110 /
13
b1000011 9
#1120000000
0!
0)
03
#1125000000
1!
1)
b10111 /
13
b1000100 9
#1130000000
0!
0)
03
#1135000000
1!
1)
b11000 /
13
b1000101 9
#1140000000
0!
0)
03
#1145000000
1!
1)
b11001 /
13
b1000110 9
#1150000000
0!
0)
03
#1155000000
1!
1)
b11010 /
13
b1000111 9
#1160000000
0!
0)
03
#1165000000
1!
1)
b11011 /
13
b1001000 9
#1170000000
0!
0)
03
#1175000000
1!
1)
b11100 /
13
b1001001 9
#1180000000
0!
0)
03
#1185000000
1!
1)
b11101 /
13
b1001010 9
#1190000000
0!
0)
03
#1195000000
1!
1)
b11110 /
13
b1001011 9
#1200000000
0!
0)
03
#1205000000
1!
1)
b11111 /
13
b1001100 9
#1210000000
0!
0)
03
#1215000000
1!
1)
b100000 /
13
b1001101 9
#1220000000
0!
0)
03
#1225000000
1!
1)
b100001 /
13
b1001110 9
#1230000000
0!
0)
03
#1235000000
1!
1)
b100010 /
13
b1001111 9
#1240000000
0!
0)
03
#1245000000
1!
1)
b100011 /
13
b1010000 9
#1250000000
0!
0)
03
#1255000000
1!
1)
b100100 /
13
b1010001 9
#1260000000
0!
0)
03
#1265000000
1!
1)
b100101 /
13
b1010010 9
#1270000000
0!
0)
03
#1275000000
1!
1)
b100110 /
13
b1010011 9
#1280000000
0!
0)
03
#1285000000
1!
1)
b100111 /
13
b1010100 9
#1290000000
0!
0)
03
#1295000000
1!
1)
b101000 /
13
b1010101 9
#1300000000
0!
0)
03
#1305000000
1!
1)
b101001 /
13
b1010110 9
#1310000000
0!
0)
03
#1315000000
1!
1)
b101010 /
13
b0 9
b1 :
#1320000000
0!
0)
03
#1325000000
1!
1)
b101011 /
13
b1 9
#1330000000
0!
0)
03
#1335000000
1!
1)
b101100 /
13
b10 9
#1340000000
0!
0)
03
#1345000000
1!
1)
b101101 /
13
b11 9
#1350000000
0!
0)
03
#1355000000
1!
1)
b101110 /
13
b100 9
#1360000000
0!
0)
03
#1365000000
1!
1)
b101111 /
13
b101 9
#1370000000
0!
0)
03
#1375000000
1!
1)
b110000 /
13
b110 9
#1380000000
0!
0)
03
#1385000000
1!
1)
b110001 /
13
b111 9
#1390000000
0!
0)
03
#1395000000
1!
1)
b110010 /
13
b1000 9
#1400000000
0!
0)
03
#1405000000
1!
1)
b110011 /
13
b1001 9
#1410000000
0!
0)
03
#1415000000
1!
1)
b110100 /
13
b1010 9
#1420000000
0!
0)
03
#1425000000
1!
1)
b110101 /
13
b1011 9
#1430000000
0!
0)
03
#1435000000
1!
1)
b110110 /
13
b1100 9
#1440000000
0!
0)
03
#1445000000
1!
1)
b110111 /
13
b1101 9
#1450000000
0!
0)
03
#1455000000
1!
1)
b111000 /
13
b1110 9
#1460000000
0!
0)
03
#1465000000
1!
1)
b111001 /
13
b1111 9
#1470000000
0!
0)
03
#1475000000
1!
1)
b111010 /
13
b10000 9
#1480000000
0!
0)
03
#1485000000
1!
1)
b111011 /
13
b10001 9
#1490000000
0!
0)
03
#1495000000
1!
1)
b111100 /
13
b10010 9
#1500000000
0!
0)
03
#1505000000
1!
1)
b111101 /
13
b10011 9
#1510000000
0!
0)
03
#1515000000
1!
1)
b111110 /
13
b10100 9
#1520000000
0!
0)
03
#1525000000
1!
1)
b111111 /
13
b10101 9
#1530000000
0!
0)
03
#1535000000
1!
1)
b1000000 /
13
b10110 9
#1540000000
0!
0)
03
#1545000000
1!
1)
b1000001 /
13
b10111 9
#1550000000
0!
0)
03
#1555000000
1!
1)
b1000010 /
13
b11000 9
#1560000000
0!
0)
03
#1565000000
1!
1)
b1000011 /
13
b11001 9
#1570000000
0!
0)
03
#1575000000
1!
1)
b1000100 /
13
b11010 9
#1580000000
0!
0)
03
#1585000000
1!
1)
b1000101 /
13
b11011 9
#1590000000
0!
0)
03
#1595000000
1!
1)
b1000110 /
13
b11100 9
#1600000000
0!
0)
03
#1605000000
1!
1)
b1000111 /
13
b11101 9
#1610000000
0!
0)
03
#1615000000
1!
1)
b1001000 /
13
b11110 9
#1620000000
0!
0)
03
#1625000000
1!
1)
b1001001 /
13
b11111 9
#1630000000
0!
0)
03
#1635000000
1!
1)
b1001010 /
13
b100000 9
#1640000000
0!
0)
03
#1645000000
1!
1)
b1001011 /
13
b100001 9
#1650000000
0!
0)
03
#1655000000
1!
1)
b1001100 /
13
b100010 9
#1660000000
0!
0)
03
#1665000000
1!
1)
b1001101 /
13
b100011 9
#1670000000
0!
0)
03
#1675000000
1!
1)
b1001110 /
13
b100100 9
#1680000000
0!
0)
03
#1685000000
1!
1)
b1001111 /
13
b100101 9
#1690000000
0!
0)
03
#1695000000
1!
1)
b1010000 /
13
b100110 9
#1700000000
0!
0)
03
#1705000000
1!
1)
b1010001 /
13
b100111 9
#1710000000
0!
0)
03
#1715000000
1!
1)
b1010010 /
13
b101000 9
#1720000000
0!
0)
03
#1725000000
1!
1)
b1010011 /
13
b101001 9
#1730000000
0!
0)
03
#1735000000
1!
1)
b1010100 /
13
b101010 9
#1740000000
0!
0)
03
#1745000000
1!
1)
b1010101 /
13
b101011 9
#1750000000
0!
0)
03
#1755000000
1!
1)
b1010110 /
13
b101100 9
#1760000000
0!
0)
03
#1765000000
1!
1)
b0 /
b1 0
13
b101101 9
#1770000000
0!
0)
03
#1775000000
1!
1)
b1 /
13
b101110 9
#1780000000
0!
0)
03
#1785000000
1!
1)
b10 /
13
b101111 9
#1790000000
0!
0)
03
#1795000000
1!
1)
b11 /
13
b110000 9
#1800000000
0!
0)
03
#1805000000
1!
1)
b100 /
13
b110001 9
#1810000000
0!
0)
03
#1815000000
1!
1)
b101 /
13
b110010 9
#1820000000
0!
0)
03
#1825000000
1!
1)
b110 /
13
b110011 9
#1830000000
0!
0)
03
#1835000000
1!
1)
b111 /
13
b110100 9
#1840000000
0!
0)
03
#1845000000
1!
1)
b1000 /
13
b110101 9
#1850000000
0!
0)
03
#1855000000
1!
1)
b1001 /
13
b110110 9
#1860000000
0!
0)
03
#1865000000
1!
1)
b1010 /
13
b110111 9
#1870000000
0!
0)
03
#1875000000
1!
1)
b1011 /
13
b111000 9
#1880000000
0!
0)
03
#1885000000
1!
1)
b1100 /
13
b111001 9
#1890000000
0!
0)
03
#1895000000
1!
1)
b1101 /
13
b111010 9
#1900000000
0!
0)
03
#1905000000
1!
1)
b1110 /
13
b111011 9
#1910000000
0!
0)
03
#1915000000
1!
1)
b1111 /
13
b111100 9
#1920000000
0!
0)
03
#1925000000
1!
1)
b10000 /
13
b111101 9
#1930000000
0!
0)
03
#1935000000
1!
1)
b10001 /
13
b111110 9
#1940000000
0!
0)
03
#1945000000
1!
1)
b10010 /
13
b111111 9
#1950000000
0!
0)
03
#1955000000
1!
1)
b10011 /
13
b1000000 9
#1960000000
0!
0)
03
#1965000000
1!
1)
b10100 /
13
b1000001 9
#1970000000
0!
0)
03
#1975000000
1!
1)
b10101 /
13
b1000010 9
#1980000000
0!
0)
03
#1985000000
1!
1)
b10110 /
13
b1000011 9
#1990000000
0!
0)
03
#1995000000
1!
1)
b10111 /
13
b1000100 9
#2000000000
0!
0)
03
#2005000000
1!
1)
b11000 /
13
b1000101 9
#2010000000
0!
0)
03
#2015000000
1!
1)
b11001 /
13
b1000110 9
#2020000000
0!
0)
03
#2025000000
1!
1)
b11010 /
13
b1000111 9
#2030000000
0!
0)
03
#2035000000
1!
1)
b11011 /
13
b1001000 9
#2040000000
0!
0)
03
#2045000000
1!
1)
b11100 /
13
b1001001 9
#2050000000
0!
0)
03
#2055000000
1!
1)
b11101 /
13
b1001010 9
#2060000000
0!
0)
03
#2065000000
1!
1)
b11110 /
13
b1001011 9
#2070000000
0!
0)
03
#2075000000
1!
1)
b11111 /
13
b1001100 9
#2080000000
0!
0)
03
#2085000000
1!
1)
b100000 /
13
b1001101 9
#2090000000
0!
0)
03
#2095000000
1!
1)
b100001 /
13
b1001110 9
#2100000000
0!
0)
03
#2105000000
1!
1)
b100010 /
13
b1001111 9
#2110000000
0!
0)
03
#2115000000
1!
1)
b100011 /
13
b1010000 9
#2120000000
0!
0)
03
#2125000000
1!
1)
b100100 /
13
b1010001 9
#2130000000
0!
0)
03
#2135000000
1!
1)
b100101 /
13
b1010010 9
#2140000000
0!
0)
03
#2145000000
1!
1)
b100110 /
13
b1010011 9
#2150000000
0!
0)
03
#2155000000
1!
1)
b100111 /
13
b1010100 9
#2160000000
0!
0)
03
#2165000000
1!
1)
b101000 /
13
b1010101 9
#2170000000
0!
0)
03
#2175000000
1!
1)
b101001 /
13
b1010110 9
#2180000000
0!
0)
03
#2185000000
1!
1)
b101010 /
13
b0 9
b10 :
#2190000000
0!
0)
03
#2195000000
1!
1)
b101011 /
13
b1 9
#2200000000
0!
0)
03
#2205000000
1!
1)
b101100 /
13
b10 9
#2210000000
0!
0)
03
#2215000000
1!
1)
b101101 /
13
b11 9
#2220000000
0!
0)
03
#2225000000
1!
1)
b101110 /
13
b100 9
#2230000000
0!
0)
03
#2235000000
1!
1)
b101111 /
13
b101 9
#2240000000
0!
0)
03
#2245000000
1!
1)
b110000 /
13
b110 9
#2250000000
0!
0)
03
#2255000000
1!
1)
b110001 /
13
b111 9
#2260000000
0!
0)
03
#2265000000
1!
1)
b110010 /
13
b1000 9
#2270000000
0!
0)
03
#2275000000
1!
1)
b110011 /
13
b1001 9
#2280000000
0!
0)
03
#2285000000
1!
1)
b110100 /
13
b1010 9
#2290000000
0!
0)
03
#2295000000
1!
1)
b110101 /
13
b1011 9
#2300000000
0!
0)
03
#2305000000
1!
1)
b110110 /
13
b1100 9
#2310000000
0!
0)
03
#2315000000
1!
1)
b110111 /
13
b1101 9
#2320000000
0!
0)
03
#2325000000
1!
1)
b111000 /
13
b1110 9
#2330000000
0!
0)
03
#2335000000
1!
1)
b111001 /
13
b1111 9
#2340000000
0!
0)
03
#2345000000
1!
1)
b111010 /
13
b10000 9
#2350000000
0!
0)
03
#2355000000
1!
1)
b111011 /
13
b10001 9
#2360000000
0!
0)
03
#2365000000
1!
1)
b111100 /
13
b10010 9
#2370000000
0!
0)
03
#2375000000
1!
1)
b111101 /
13
b10011 9
#2380000000
0!
0)
03
#2385000000
1!
1)
b111110 /
13
b10100 9
#2390000000
0!
0)
03
#2395000000
1!
1)
b111111 /
13
b10101 9
#2400000000
0!
0)
03
#2405000000
1!
1)
b1000000 /
13
b10110 9
#2410000000
0!
0)
03
#2415000000
1!
1)
b1000001 /
13
b10111 9
#2420000000
0!
0)
03
#2425000000
1!
1)
b1000010 /
13
b11000 9
#2430000000
0!
0)
03
#2435000000
1!
1)
b1000011 /
13
b11001 9
#2440000000
0!
0)
03
#2445000000
1!
1)
b1000100 /
13
b11010 9
#2450000000
0!
0)
03
#2455000000
1!
1)
b1000101 /
13
b11011 9
#2460000000
0!
0)
03
#2465000000
1!
1)
b1000110 /
13
b11100 9
#2470000000
0!
0)
03
#2475000000
1!
1)
b1000111 /
13
b11101 9
#2480000000
0!
0)
03
#2485000000
1!
1)
b1001000 /
13
b11110 9
#2490000000
0!
0)
03
#2495000000
1!
1)
b1001001 /
13
b11111 9
#2500000000
0!
0)
03
#2505000000
1!
1)
b1001010 /
13
b100000 9
#2510000000
0!
0)
03
#2515000000
1!
1)
b1001011 /
13
b100001 9
#2520000000
0!
0)
03
#2525000000
1!
1)
b1001100 /
13
b100010 9
#2530000000
0!
0)
03
#2535000000
1!
1)
b1001101 /
13
b100011 9
#2540000000
0!
0)
03
#2545000000
1!
1)
b1001110 /
13
b100100 9
#2550000000
0!
0)
03
#2555000000
1!
1)
b1001111 /
13
b100101 9
