uart_rx.vhd
library ieee;
use ieee.std_logic_1164.all;
use ieee.numeric_std.all;

entity uart_rx is
  generic (
    g_CLKS_PER_BIT : integer := 870
  );
  port (
    i_clk       : in  std_logic;
    i_rx_serial : in  std_logic;
    o_rx_dv     : out std_logic;
    o_rx_byte   : out std_logic_vector(7 downto 0)
  );
end uart_rx;

architecture rtl of uart_rx is
  type t_SM_Main is (IDLE, RX_START_BIT, RX_DATA_BITS, RX_STOP_BIT, CLEANUP);
  signal r_SM_Main : t_SM_Main := IDLE;

  signal r_Rx_Data_R : std_logic := '0';
  signal r_Rx_Data   : std_logic := '0';

  signal r_Clk_Count : integer range 0 to g_CLKS_PER_BIT-1 := 0;
  signal r_Bit_Index : integer range 0 to 7 := 0;
  signal r_Rx_Byte   : std_logic_vector(7 downto 0) := (others => '0');
  signal r_Rx_DV     : std_logic := '0';

begin
  -- Purpose: Double-register the incoming data for metastability issues
  p_SAMPLE : process (i_clk)
  begin
    if rising_edge(i_clk) then
      r_Rx_Data_R <= i_rx_serial;
      r_Rx_Data   <= r_Rx_Data_R;
    end if;
  end process p_SAMPLE;

  p_UART_RX : process (i_clk)
  begin
    if rising_edge(i_clk) then
      case r_SM_Main is

        when IDLE =>
          r_Rx_DV     <= '0';
          r_Clk_Count <= 0;
          r_Bit_Index <= 0;

          if r_Rx_Data = '0' then -- Start bit detected
            r_SM_Main <= RX_START_BIT;
          else
            r_SM_Main <= IDLE;
          end if;

        -- Check middle of start bit to confirm it's still low
        when RX_START_BIT =>
          if r_Clk_Count = (g_CLKS_PER_BIT-1)/2 then
            if r_Rx_Data = '0' then
              r_Clk_Count <= 0;  -- reset counter, found the middle
              r_SM_Main   <= RX_DATA_BITS;
            else
              r_SM_Main <= IDLE;
            end if;
          else
            r_Clk_Count <= r_Clk_Count + 1;
            r_SM_Main   <= RX_START_BIT;
          end if;

        when RX_DATA_BITS =>
          if r_Clk_Count < g_CLKS_PER_BIT-1 then
            r_Clk_Count <= r_Clk_Count + 1;
            r_SM_Main   <= RX_DATA_BITS;
          else
            r_Clk_Count            <= 0;
            r_Rx_Byte(r_Bit_Index) <= r_Rx_Data;

            if r_Bit_Index < 7 then
              r_Bit_Index <= r_Bit_Index + 1;
              r_SM_Main   <= RX_DATA_BITS;
            else
              r_Bit_Index <= 0;
              r_SM_Main   <= RX_STOP_BIT;
            end if;
          end if;

        when RX_STOP_BIT =>
          -- Wait g_CLKS_PER_BIT-1 (Stop Bit Duration)
          if r_Clk_Count < g_CLKS_PER_BIT-1 then
            r_Clk_Count <= r_Clk_Count + 1;
            r_SM_Main   <= RX_STOP_BIT;
          else
            r_Rx_DV     <= '1';
            r_Clk_Count <= 0;
            r_SM_Main   <= CLEANUP;
          end if;

        when CLEANUP =>
          r_SM_Main <= IDLE;
          r_Rx_DV   <= '0';

        when others =>
          r_SM_Main <= IDLE;
      end case;
    end if;
  end process p_UART_RX;

  o_rx_dv   <= r_Rx_DV;
  o_rx_byte <= r_Rx_Byte;
end rtl;

uart_tx.vhd
library ieee;
use ieee.std_logic_1164.all;
use ieee.numeric_std.all;

entity uart_tx is
  generic (
    g_CLKS_PER_BIT : integer := 870  -- (Frequency / BaudRate) already calculated by the user
  );
  port (
    i_clk       : in  std_logic;
    i_tx_dv     : in  std_logic; -- Data Valid pulse
    i_tx_byte   : in  std_logic_vector(7 downto 0);
    o_tx_active : out std_logic;
    o_tx_serial : out std_logic;
    o_tx_done   : out std_logic
  );
end uart_tx;

architecture rtl of uart_tx is
  type t_SM_Main is (IDLE, TX_START_BIT, TX_DATA_BITS, TX_STOP_BIT, CLEANUP);
  signal r_SM_Main : t_SM_Main := IDLE;

  signal r_Clk_Count : integer range 0 to g_CLKS_PER_BIT-1 := 0;
  signal r_Bit_Index : integer range 0 to 7 := 0;
  signal r_Tx_Data   : std_logic_vector(7 downto 0) := (others => '0');
  signal r_Tx_Done   : std_logic := '0';

begin
  p_UART_TX : process (i_clk)
  begin
    if rising_edge(i_clk) then
      case r_SM_Main is

        when IDLE =>
          o_tx_active <= '0';
          o_tx_serial <= '1'; -- Idle high
          r_Tx_Done   <= '0';
          r_Clk_Count <= 0;
          r_Bit_Index <= 0;

          if i_tx_dv = '1' then
            r_Tx_Data <= i_tx_byte;
            r_SM_Main <= TX_START_BIT;
          else
            r_SM_Main <= IDLE;
          end if;

        -- Send Start Bit (Low)
        when TX_START_BIT =>
          o_tx_active <= '1';
          o_tx_serial <= '0';

          if r_Clk_Count < g_CLKS_PER_BIT-1 then
            r_Clk_Count <= r_Clk_Count + 1;
            r_SM_Main   <= TX_START_BIT;
          else
            r_Clk_Count <= 0;
            r_SM_Main   <= TX_DATA_BITS;
          end if;

        -- Send Data Bits
        when TX_DATA_BITS =>
          o_tx_serial <= r_Tx_Data(r_Bit_Index);

          if r_Clk_Count < g_CLKS_PER_BIT-1 then
            r_Clk_Count <= r_Clk_Count + 1;
            r_SM_Main   <= TX_DATA_BITS;
          else
            r_Clk_Count <= 0;
            if r_Bit_Index < 7 then
              r_Bit_Index <= r_Bit_Index + 1;
              r_SM_Main   <= TX_DATA_BITS;
            else
              r_Bit_Index <= 0;
              r_SM_Main   <= TX_STOP_BIT;
            end if;
          end if;

        -- Send Stop Bit (High)
        when TX_STOP_BIT =>
          o_tx_serial <= '1';

          if r_Clk_Count < g_CLKS_PER_BIT-1 then
            r_Clk_Count <= r_Clk_Count + 1;
            r_SM_Main   <= TX_STOP_BIT;
          else
            r_Tx_Done   <= '1';
            r_Clk_Count <= 0;
            r_SM_Main   <= CLEANUP;
          end if;

        when CLEANUP =>
          o_tx_active <= '0';
          r_Tx_Done   <= '1';
          r_SM_Main   <= IDLE;

        when others =>
          r_SM_Main <= IDLE;
      end case;
    end if;
  end process p_UART_TX;

  o_tx_done <= r_Tx_Done;
end rtl;

uart_tb.vhd
library ieee;
use ieee.std_logic_1164.all;
use ieee.numeric_std.all;

entity uart_tb is
end uart_tb;

architecture behave of uart_tb is
  constant c_CLK_PERIOD : time := 10 ns; -- 100 MHz
  constant c_CLKS_PER_BIT : integer := 5; -- Number of clock cycles per bit this is calculated as 10 ns / (1/115200) = 87

  signal r_Clk : std_logic := '0';
  signal w_Tx_Serial : std_logic;

  -- TX Signals
  signal r_Tx_Dv   : std_logic := '0';
  signal r_Tx_Byte : std_logic_vector(7 downto 0) := (others => '0');
  signal w_Tx_Active : std_logic;
  signal w_Tx_Done   : std_logic;

  -- RX Signals
  signal w_Rx_Dv   : std_logic;
  signal w_Rx_Byte : std_logic_vector(7 downto 0);

begin
  -- Clock Generator
  r_Clk <= not r_Clk after c_CLK_PERIOD/2;


  UART_TX_INST : entity work.uart_tx
    generic map (g_CLKS_PER_BIT => c_CLKS_PER_BIT)
    port map (
      i_clk       => r_Clk,
      i_tx_dv     => r_Tx_Dv,
      i_tx_byte   => r_Tx_Byte,
      o_tx_active => w_Tx_Active,
      o_tx_serial => w_Tx_Serial,
      o_tx_done   => w_Tx_Done
    );

  -- Instantiate UART Receiver
  UART_RX_INST : entity work.uart_rx
    generic map (g_CLKS_PER_BIT => c_CLKS_PER_BIT)
    port map (
      i_clk       => r_Clk,
      i_rx_serial => w_Tx_Serial,
      o_rx_dv     => w_Rx_Dv,
      o_rx_byte   => w_Rx_Byte
    );

    -- Main Stimulus Process
      p_TEST : process
      begin
        wait until rising_edge(r_Clk);
        wait until rising_edge(r_Clk);

        -- Send a byte: 0x37 (00110111)
        r_Tx_Dv   <= '1';
        r_Tx_Byte <= X"10";
        wait until rising_edge(r_Clk);
        r_Tx_Dv   <= '0';


        wait until w_Rx_Dv = '1';


        assert w_Rx_Byte = X"10"
          report "Test Failed: Received wrong byte" severity failure;

        report "Test Passed: Sent 0x10 and Received " & to_hstring(w_Rx_Byte);

        wait for 1 us;

        assert false report "Simulation Finished Successfully";
        wait;
      end process;

end behave;

wave.vcd
$date
  Thu Dec 04 18:55:58 2025
$end
$version
  GHDL v0
$end
$timescale
  1 fs
$end
$scope module standard $end
$upscope $end
$scope module textio $end
$upscope $end
$scope module std_logic_1164 $end
$upscope $end
$scope module numeric_std $end
$upscope $end
$scope module uart_tb $end
$var reg 1 ! r_clk $end
$var reg 1 " w_tx_serial $end
$var reg 1 # r_tx_dv $end
$var reg 8 $ r_tx_byte[7:0] $end
$var reg 1 % w_tx_active $end
$var reg 1 & w_tx_done $end
$var reg 1 ' w_rx_dv $end
$var reg 8 ( w_rx_byte[7:0] $end
$scope module uart_tx_inst $end
$var reg 1 ) i_clk $end
$var reg 1 * i_tx_dv $end
$var reg 8 + i_tx_byte[7:0] $end
$var reg 1 , o_tx_active $end
$var reg 1 - o_tx_serial $end
$var reg 1 . o_tx_done $end
$comment r_sm_main is not handled $end
$var integer 32 / r_clk_count $end
$var integer 32 0 r_bit_index $end
$var reg 8 1 r_tx_data[7:0] $end
$var reg 1 2 r_tx_done $end
$upscope $end
$scope module uart_rx_inst $end
$var reg 1 3 i_clk $end
$var reg 1 4 i_rx_serial $end
$var reg 1 5 o_rx_dv $end
$var reg 8 6 o_rx_byte[7:0] $end
$comment r_sm_main is not handled $end
$var reg 1 7 r_rx_data_r $end
$var reg 1 8 r_rx_data $end
$var integer 32 9 r_clk_count $end
$var integer 32 : r_bit_index $end
$var reg 8 ; r_rx_byte[7:0] $end
$var reg 1 < r_rx_dv $end
$upscope $end
$upscope $end
$enddefinitions $end
#0
0!
U"
0#
b00000000 $
U%
0&
0'
b00000000 (
0)
0*
b00000000 +
U,
U-
0.
b0 /
b0 0
b00000000 1
02
03
U4
05
b00000000 6
07
08
b0 9
b0 :
b00000000 ;
0<
#5000000
1!
1"
0%
1)
0,
1-
13
14
U7
#10000000
0!
0)
03
#15000000
1!
1#
b00010000 $
1)
1*
b00010000 +
13
17
U8
b1 9
#20000000
0!
0)
03
#25000000
1!
0#
1)
0*
b00010000 1
13
18
b10 9
#30000000
0!
0)
03
#35000000
1!
0"
1%
1)
1,
0-
b1 /
13
04
#40000000
0!
0)
03
#45000000
1!
1)
b10 /
13
07
b0 9
#50000000
0!
0)
03
#55000000
1!
1)
b11 /
13
08
#60000000
0!
0)
03
#65000000
1!
1)
b100 /
13
#70000000
0!
0)
03
#75000000
1!
1)
b0 /
13
b1 9
#80000000
0!
0)
03
#85000000
1!
1)
b1 /
13
b10 9
#90000000
0!
0)
03
#95000000
1!
1)
b10 /
13
b0 9
#100000000
0!
0)
03
#105000000
1!
1)
b11 /
13
b1 9
#110000000
0!
0)
03
#115000000
1!
1)
b100 /
13
b10 9
#120000000
0!
0)
03
#125000000
1!
1)
b0 /
b1 0
13
b11 9
#130000000
0!
0)
03
#135000000
1!
1)
b1 /
13
b100 9
#140000000
0!
0)
03
#145000000
1!
1)
b10 /
13
b0 9
b1 :
#150000000
0!
0)
03
#155000000
1!
1)
b11 /
13
b1 9
#160000000
0!
0)
03
#165000000
1!
1)
b100 /
13
b10 9
#170000000
0!
0)
03
#175000000
1!
1)
b0 /
b10 0
13
b11 9
#180000000
0!
0)
03
#185000000
1!
1)
b1 /
13
b100 9
#190000000
0!
0)
03
#195000000
1!
1)
b10 /
13
b0 9
b10 :
#200000000
0!
0)
03
#205000000
1!
1)
b11 /
13
b1 9
#210000000
0!
0)
03
#215000000
1!
1)
b100 /
13
b10 9
#220000000
0!
0)
03
#225000000
1!
1)
b0 /
b11 0
13
b11 9
#230000000
0!
0)
03
#235000000
1!
1)
b1 /
13
b100 9
#240000000
0!
0)
03
#245000000
1!
1)
b10 /
13
b0 9
b11 :
#250000000
0!
0)
03
#255000000
1!
1)
b11 /
13
b1 9
#260000000
0!
0)
03
#265000000
1!
1)
b100 /
13
b10 9
#270000000
0!
0)
03
#275000000
1!
1)
b0 /
b100 0
13
b11 9
#280000000
0!
0)
03
#285000000
1!
1"
1)
1-
b1 /
13
14
b100 9
#290000000
0!
0)
03
#295000000
1!
1)
b10 /
13
17
b0 9
b100 :
#300000000
0!
0)
03
#305000000
1!
1)
b11 /
13
18
b1 9
#310000000
0!
0)
03
#315000000
1!
1)
b100 /
13
b10 9
#320000000
0!
0)
03
#325000000
1!
1)
b0 /
b101 0
13
b11 9
#330000000
0!
0)
03
#335000000
1!
0"
1)
0-
b1 /
13
04
b100 9
#340000000
0!
0)
03
#345000000
1!
b00010000 (
1)
b10 /
13
b00010000 6
07
b0 9
b101 :
b00010000 ;
#350000000
0!
0)
03
#355000000
1!
1)
b11 /
13
08
b1 9
#360000000
0!
0)
03
#365000000
1!
1)
b100 /
13
b10 9
#370000000
0!
0)
03
#375000000
1!
1)
b0 /
b110 0
13
b11 9
#380000000
0!
0)
03
#385000000
1!
1)
b1 /
13
b100 9
#390000000
0!
0)
03
#395000000
1!
1)
b10 /
13
b0 9
b110 :
#400000000
0!
0)
03
#405000000
1!
1)
b11 /
13
b1 9
#410000000
0!
0)
03
#415000000
1!
1)
b100 /
13
b10 9
#420000000
0!
0)
03
#425000000
1!
1)
b0 /
b111 0
13
b11 9
#430000000
0!
0)
03
#435000000
1!
1)
b1 /
13
b100 9
#440000000
0!
0)
03
#445000000
1!
1)
b10 /
13
b0 9
b111 :
#450000000
0!
0)
03
#455000000
1!
1)
b11 /
13
b1 9
#460000000
0!
0)
03
#465000000
1!
1)
b100 /
13
b10 9
#470000000
0!
0)
03
#475000000
1!
1)
b0 /
b0 0
13
b11 9
#480000000
0!
0)
03
#485000000
1!
1"
1)
1-
b1 /
13
14
b100 9
#490000000
0!
0)
03
#495000000
1!
1)
b10 /
13
17
b0 9
b0 :
#500000000
0!
0)
03
#505000000
1!
1)
b11 /
13
18
b1 9
#510000000
0!
0)
03
#515000000
1!
1)
b100 /
13
b10 9
#520000000
0!
0)
03
#525000000
1!
1&
1)
1.
b0 /
12
13
b11 9
#530000000
0!
0)
03
#535000000
1!
0%
1)
0,
13
b100 9
#540000000
0!
0)
03
#545000000
1!
0&
1'
1)
0.
02
13
15
b0 9
1<
#550000000
0!
0)
03
#555000000
1!
0'
1)
13
05
0<
